lin_mil/Lin_MIL.py
lin_mil/__init__.py
lin_mil/attention/__init__.py
lin_mil/attention/ablation_utils.py
lin_mil/attention/dilated_attention.py
lin_mil/attention/linear_attention.py
lin_mil/attention/nystrom_attention.py
lin_mil/attention/softmax_attention.py
lin_mil-1.0.1.dist-info/licenses/LICENSE
lin_mil-1.0.1.dist-info/METADATA
lin_mil-1.0.1.dist-info/WHEEL
lin_mil-1.0.1.dist-info/top_level.txt
lin_mil-1.0.1.dist-info/RECORD
